pianovis/__init__.py
pianovis/constants.py
pianovis/examples.py
pianovis/utils.py
pianovis/video.py
pianovis/app/__init__.py
pianovis/app/app.py
piano_vis-0.2.1.dist-info/LICENSE
piano_vis-0.2.1.dist-info/METADATA
piano_vis-0.2.1.dist-info/WHEEL
piano_vis-0.2.1.dist-info/top_level.txt
piano_vis-0.2.1.dist-info/RECORD
